[
    {
      "id": "1",
      "title": "hello world",
      "content": "A tutorial introduction to the programming language B."
    },
    {
      "id": "2",
      "title": "well, would you look at that",
      "content": "i mean, would you just look at that right there? juss lookatit."
    },
    {
      "id": "3",
      "title": "the quick brown fox",
      "content": "jumps over the lazy dog."
    },
    {
      "id": "4",
      "title": "i almost had you",
      "content": "you almost had me? you never had me. you never had your car."
    },
    {
      "id": "5",
      "title": "i am groot",
      "content": "i am groot."
    }
  ]